bstacksnoadbclick/README.MD
bstacksnoadbclick/__init__.py
bstacksnoadbclick/requirements.txt
bstacksnoadbclick/thirdparty.json
bstacksnoadbclick-0.10.dist-info/LICENSE.rst
bstacksnoadbclick-0.10.dist-info/METADATA
bstacksnoadbclick-0.10.dist-info/WHEEL
bstacksnoadbclick-0.10.dist-info/top_level.txt
bstacksnoadbclick-0.10.dist-info/RECORD
