Metadata-Version: 2.1
Name: bstacksnoadbclick
Version: 0.10
Summary: like input tap for BlueStacks instances, but without using ADB
Home-page: https://github.com/hansalemaos/bstacksnoadbclick
Author: Johannes Fischer
Author-email: aulasparticularesdealemaosp@gmail.com
License: MIT
Keywords: bluestacks,click
Classifier: Development Status :: 4 - Beta
Classifier: Programming Language :: Python :: 3 :: Only
Classifier: Programming Language :: Python :: 3.10
Classifier: Topic :: Software Development :: Libraries :: Python Modules
Classifier: Topic :: Utilities
License-File: LICENSE.rst
Requires-Dist: ctypes-window-info
Requires-Dist: mousekey
